qrgenerator/__init__.py
qr_generator-1.0.0.dist-info/LICENSE
qr_generator-1.0.0.dist-info/METADATA
qr_generator-1.0.0.dist-info/WHEEL
qr_generator-1.0.0.dist-info/entry_points.txt
qr_generator-1.0.0.dist-info/top_level.txt
qr_generator-1.0.0.dist-info/RECORD
