Metadata-Version: 2.1
Name: qr-generator
Version: 1.0.0
Summary: QR Code image generator
Author-email: ChemicalLuck <j.tebbett@outlook.com>
Classifier: Development Status :: 5 - Production/Stable
Classifier: License :: OSI Approved :: MIT License
Classifier: Operating System :: OS Independent
Classifier: Intended Audience :: Developers
Classifier: Programming Language :: Python
Classifier: Programming Language :: Python :: 3
Classifier: Programming Language :: Python :: 3.7
Classifier: Topic :: Multimedia :: Graphics
Classifier: Topic :: Software Development :: Libraries :: Python Modules
Requires-Python: >=3.7
License-File: LICENSE
Requires-Dist: pillow ==10.3.0
Requires-Dist: pypng ==0.20220715.0
Requires-Dist: qrcode ==7.4.2
Requires-Dist: ruff ==0.4.2
Requires-Dist: typing-extensions ==4.11.0
